lost_cat_medical/__init__.py
lost_cat_medical/parsers/__init__.py
lost_cat_medical/parsers/dicom_parser.py
lost_cat_medical/processors/__init__.py
lost_cat_medical/processors/dicom_processor.py
lost_cat_medical/utils/__init__.py
lost_cat_medical/utils/dicom_utils.py
lost_cat_medical/utils/web_helper.py
lost_cat_medical-0.0.5.dist-info/LICENSE
lost_cat_medical-0.0.5.dist-info/METADATA
lost_cat_medical-0.0.5.dist-info/WHEEL
lost_cat_medical-0.0.5.dist-info/top_level.txt
lost_cat_medical-0.0.5.dist-info/RECORD
