Metadata-Version: 2.1
Name: lost-cat-medical
Version: 0.0.5
Summary: Lost Cat (medical) is a package for medical related uris
Author-email: Dreffed aka David Gloyn-Cox <dreffed@gmail.com>, Thoughtswin Systems Inc <david.gloyn-cox@thoughtswinsystems.com>
License: MIT License
Project-URL: Homepage, https://github.com/thoughtswinsystems/lost_cat_medical
Project-URL: Bug Tracker, https://github.com/thoughtswinsystems/lost_cat_medical/issues
Classifier: Programming Language :: Python :: 3
Classifier: License :: OSI Approved :: MIT License
Classifier: Operating System :: OS Independent
Requires-Python: >=3.8
License-File: LICENSE
Requires-Dist: lost-cat (>=0.1.0)
Requires-Dist: numpy
Requires-Dist: pillow
Requires-Dist: pydicom
Requires-Dist: pynetdicom
